odoo8_addon_donation_tax_receipt-8.0.0.2.0.99.dev7-py2.7-nspkg.pth
odoo8_addon_donation_tax_receipt-8.0.0.2.0.99.dev7.dist-info/DESCRIPTION.rst
odoo8_addon_donation_tax_receipt-8.0.0.2.0.99.dev7.dist-info/METADATA
odoo8_addon_donation_tax_receipt-8.0.0.2.0.99.dev7.dist-info/RECORD
odoo8_addon_donation_tax_receipt-8.0.0.2.0.99.dev7.dist-info/WHEEL
odoo8_addon_donation_tax_receipt-8.0.0.2.0.99.dev7.dist-info/metadata.json
odoo8_addon_donation_tax_receipt-8.0.0.2.0.99.dev7.dist-info/namespace_packages.txt
odoo8_addon_donation_tax_receipt-8.0.0.2.0.99.dev7.dist-info/top_level.txt
odoo_addons/donation_tax_receipt/README.rst
odoo_addons/donation_tax_receipt/__init__.py
odoo_addons/donation_tax_receipt/__openerp__.py
odoo_addons/donation_tax_receipt/donation_tax.py
odoo_addons/donation_tax_receipt/donation_tax_data.xml
odoo_addons/donation_tax_receipt/donation_tax_demo.xml
odoo_addons/donation_tax_receipt/donation_tax_view.xml
odoo_addons/donation_tax_receipt/partner.py
odoo_addons/donation_tax_receipt/partner_view.xml
odoo_addons/donation_tax_receipt/product.py
odoo_addons/donation_tax_receipt/product_view.xml
odoo_addons/donation_tax_receipt/report.xml
odoo_addons/donation_tax_receipt/i18n/fr.po
odoo_addons/donation_tax_receipt/report/__init__.py
odoo_addons/donation_tax_receipt/report/donation_report.py
odoo_addons/donation_tax_receipt/report/donation_report_view.xml
odoo_addons/donation_tax_receipt/report/report_donationtax.xml
odoo_addons/donation_tax_receipt/security/ir.model.access.csv
odoo_addons/donation_tax_receipt/security/tax_receipt_security.xml
odoo_addons/donation_tax_receipt/static/description/icon.png
odoo_addons/donation_tax_receipt/test/annual_tax_receipt.yml
odoo_addons/donation_tax_receipt/test/each_tax_receipt.yml
odoo_addons/donation_tax_receipt/wizard/__init__.py
odoo_addons/donation_tax_receipt/wizard/tax_receipt_annual_create.py
odoo_addons/donation_tax_receipt/wizard/tax_receipt_annual_create_view.xml
odoo_addons/donation_tax_receipt/wizard/tax_receipt_option_switch.py
odoo_addons/donation_tax_receipt/wizard/tax_receipt_option_switch_view.xml
odoo_addons/donation_tax_receipt/wizard/tax_receipt_print.py
odoo_addons/donation_tax_receipt/wizard/tax_receipt_print_view.xml
